mvllm/__init__.py
mvllm/cli.py
mvllm/config.py
mvllm/load_manager.py
mvllm/main.py
mvllm/routes.py
mvllm/server_manager.py
mvllm-0.1.0.dist-info/METADATA
mvllm-0.1.0.dist-info/WHEEL
mvllm-0.1.0.dist-info/entry_points.txt
mvllm-0.1.0.dist-info/licenses/LICENSE
mvllm-0.1.0.dist-info/RECORD
