Metadata-Version: 2.4
Name: mvllm
Version: 0.1.0
Summary: A FastAPI-based load balancer for vLLM servers with OpenAI-compatible API
Project-URL: Homepage, https://github.com/xerrors/mvllm
Project-URL: Repository, https://github.com/xerrors/mvllm
Project-URL: Issues, https://github.com/xerrors/mvllm/issues
Project-URL: Documentation, https://github.com/xerrors/mvllm#readme
Author-email: Wenjie Zhang <xerrors@163.com>
License: MIT License
License-File: LICENSE
Keywords: fastapi,gpu,inference,llm,load-balancer,openai,vllm
Classifier: Development Status :: 4 - Beta
Classifier: Framework :: FastAPI
Classifier: Intended Audience :: Developers
Classifier: Intended Audience :: Science/Research
Classifier: License :: OSI Approved :: MIT License
Classifier: Operating System :: OS Independent
Classifier: Programming Language :: Python :: 3
Classifier: Programming Language :: Python :: 3.10
Classifier: Programming Language :: Python :: 3.11
Classifier: Programming Language :: Python :: 3.12
Classifier: Topic :: Scientific/Engineering :: Artificial Intelligence
Classifier: Topic :: System :: Distributed Computing
Requires-Python: >=3.10
Requires-Dist: aiohttp>=3.12.15
Requires-Dist: fastapi>=0.104.0
Requires-Dist: httpx>=0.25.0
Requires-Dist: loguru>=0.7.0
Requires-Dist: openai
Requires-Dist: psutil>=7.1.0
Requires-Dist: pydantic>=2.5.0
Requires-Dist: requests>=2.32.5
Requires-Dist: rich>=14.1.0
Requires-Dist: toml>=0.10.2
Requires-Dist: typer>=0.19.2
Requires-Dist: uvicorn>=0.24.0
